nuvom/__init__.py
nuvom/__version__.py
nuvom/config.py
nuvom/job.py
nuvom/log.py
nuvom/queue.py
nuvom/result_store.py
nuvom/sdk.py
nuvom/serialize.py
nuvom/task.py
nuvom/watcher.py
nuvom/worker.py
nuvom/cli/cli.py
nuvom/cli/commands/discover_tasks.py
nuvom/cli/commands/history.py
nuvom/cli/commands/inspect_job.py
nuvom/cli/commands/list_tasks.py
nuvom/cli/commands/plugin.py
nuvom/cli/commands/runtestworker.py
nuvom/discovery/compute_path.py
nuvom/discovery/discover_tasks.py
nuvom/discovery/filters.py
nuvom/discovery/loader.py
nuvom/discovery/manifest.py
nuvom/discovery/parser.py
nuvom/discovery/reference.py
nuvom/discovery/walker.py
nuvom/execution/job_runner.py
nuvom/internal/manifest.py
nuvom/plugins/contracts.py
nuvom/plugins/loader.py
nuvom/plugins/registry.py
nuvom/plugins/monitoring/prometheus.py
nuvom/queue_backends/base.py
nuvom/queue_backends/file_queue.py
nuvom/queue_backends/memory_queue.py
nuvom/queue_backends/sqlite_queue.py
nuvom/registry/auto_register.py
nuvom/registry/registry.py
nuvom/result_backends/base.py
nuvom/result_backends/file_backend.py
nuvom/result_backends/memory_backend.py
nuvom/result_backends/sqlite_backend.py
nuvom/scheduler/__init__.py
nuvom/scheduler/backend.py
nuvom/scheduler/dispatcher.py
nuvom/scheduler/memory_backend.py
nuvom/scheduler/models.py
nuvom/scheduler/scheduler.py
nuvom/scheduler/sqlite_backend.py
nuvom/scheduler/worker.py
nuvom/serialization/base.py
nuvom/serialization/msgpack_serializer.py
nuvom/utils/compat_utils/tomllib_compat.py
nuvom/utils/file_utils/safe_remove.py
nuvom-0.11.2.dist-info/METADATA
nuvom-0.11.2.dist-info/WHEEL
nuvom-0.11.2.dist-info/entry_points.txt
nuvom-0.11.2.dist-info/licenses/LICENSE
nuvom-0.11.2.dist-info/RECORD
