Metadata-Version: 2.4
Name: nuvom
Version: 0.11.2
Summary: Nuvom gives developers a task engine they can trust: clean APIs, predictable behavior, and production-ready task scheduling for Python.
Project-URL: Homepage, https://github.com/nahom-zewdu/Nuvom
Project-URL: Repository, https://github.com/nahom-zewdu/Nuvom
Author-email: Nahom <nahiyo86@gmail.com>
License-Expression: Apache-2.0
License-File: LICENSE
Requires-Python: >=3.8
Requires-Dist: croniter>=1.3.8
Requires-Dist: msgpack>=1.1.0
Requires-Dist: pathspec>=0.12.1
Requires-Dist: pydantic-settings>=2.9.1
Requires-Dist: pydantic>=2.0.0
Requires-Dist: python-dotenv>=1.1.0
Requires-Dist: requests>=2.32.0
Requires-Dist: rich>=13.0.0
Requires-Dist: tomli; python_version < '3.11'
Requires-Dist: typer<0.12.0,>=0.7.0
Requires-Dist: tzdata>=2025.2
Requires-Dist: watchdog>=6.0.0
